binance_sdk_simple_earn/__init__.py
binance_sdk_simple_earn/metadata.py
binance_sdk_simple_earn/rest_api/__init__.py
binance_sdk_simple_earn/rest_api/api/__init__.py
binance_sdk_simple_earn/rest_api/api/bfusd_api.py
binance_sdk_simple_earn/rest_api/api/flexible_locked_api.py
binance_sdk_simple_earn/rest_api/api/rwusd_api.py
binance_sdk_simple_earn/rest_api/models/__init__.py
binance_sdk_simple_earn/rest_api/models/enums.py
binance_sdk_simple_earn/rest_api/models/get_bfusd_account_response.py
binance_sdk_simple_earn/rest_api/models/get_bfusd_quota_details_response.py
binance_sdk_simple_earn/rest_api/models/get_bfusd_quota_details_response_fast_redemption_quota.py
binance_sdk_simple_earn/rest_api/models/get_bfusd_quota_details_response_standard_redemption_quota.py
binance_sdk_simple_earn/rest_api/models/get_bfusd_rate_history_response.py
binance_sdk_simple_earn/rest_api/models/get_bfusd_rate_history_response_rows_inner.py
binance_sdk_simple_earn/rest_api/models/get_bfusd_redemption_history_response.py
binance_sdk_simple_earn/rest_api/models/get_bfusd_redemption_history_response_rows_inner.py
binance_sdk_simple_earn/rest_api/models/get_bfusd_rewards_history_response.py
binance_sdk_simple_earn/rest_api/models/get_bfusd_rewards_history_response_rows_inner.py
binance_sdk_simple_earn/rest_api/models/get_bfusd_subscription_history_response.py
binance_sdk_simple_earn/rest_api/models/get_bfusd_subscription_history_response_rows_inner.py
binance_sdk_simple_earn/rest_api/models/get_collateral_record_response.py
binance_sdk_simple_earn/rest_api/models/get_collateral_record_response_rows_inner.py
binance_sdk_simple_earn/rest_api/models/get_flexible_personal_left_quota_response.py
binance_sdk_simple_earn/rest_api/models/get_flexible_product_position_response.py
binance_sdk_simple_earn/rest_api/models/get_flexible_product_position_response_rows_inner.py
binance_sdk_simple_earn/rest_api/models/get_flexible_product_position_response_rows_inner_tier_annual_percentage_rate.py
binance_sdk_simple_earn-6.0.0.dist-info/METADATA
binance_sdk_simple_earn-6.0.0.dist-info/WHEEL
binance_sdk_simple_earn-6.0.0.dist-info/licenses/LICENCE
binance_sdk_simple_earn-6.0.0.dist-info/RECORD
